FIFO/FIFO.v
.//FIFO - single clock hardware block

module FIFO(clk , rst , buf_in , buf_out , wr_en , rd_en , buf_empty , buf_full , fifo_counter);

input clk , rst ,wr_en,rd_en;
input  [7:0] buf_in;
output reg [7:0] buf_out;
output reg [6:0] fifo_counter;
output buf_empty,buf_full;


reg [7:0] buf_mem [63:0] ;  // 8bit data having elements 64 //memory store
reg [5:0] w_ptr , r_ptr;

//always @(fifo_counter) begin
//buf_empty = (fifo_counter == 0);
//buf_full = (fifo_counter == 64);
//end

assign buf_empty = (fifo_counter == 0);
assign buf_full  = (fifo_counter == 64);


//dealing with fifo_counter 
always @(posedge clk or posedge rst) begin

if(rst)
fifo_counter <=  0;
else if((!buf_full && wr_en) && (!buf_empty && rd_en))
fifo_counter <= fifo_counter;
else if(!buf_full && wr_en)
fifo_counter <= fifo_counter + 1'b1;
else if(!buf_empty && rd_en)
fifo_counter <= fifo_counter - 1'b1;

else
fifo_counter <= fifo_counter;
end

//helps to fetch data

always @(posedge clk or posedge rst)
begin
if(rst)
 buf_out <= 8'd0;
 else
begin
if(rd_en && !buf_empty)
buf_out <= buf_mem[r_ptr];
else
buf_out <= buf_out;

end
end

 //helps to writing data into fifo

always @(posedge clk )
begin
if(wr_en && !buf_full)
buf_mem[w_ptr] <= buf_in;  // with wptr we get address 
//else
//buf_mem[w_ptr]  <= buf_mem[w_ptr] ;
end


//now we manage the pointers

//manageing head pointers
always @(posedge clk or posedge rst)
begin
if(rst)
begin
w_ptr <=0;
r_ptr <=0;
end
//both happens simultaously /concurrently within this else block

else begin
//write 
    if(!buf_full && wr_en)
    w_ptr <= w_ptr + 1;
else
w_ptr <= w_ptr;

//read

if(!buf_empty && rd_en)
r_ptr <= r_ptr + 1;
else
r_ptr <= r_ptr;  //tail cant overtake head
 
end

end


endmodule

FIFO/FIFO_tb.v
`timescale 1ns/1ps

module FIFO_tb;

reg clk;
reg rst;
reg wr_en;
reg rd_en;
reg [7:0] buf_in;

wire [7:0] buf_out;
wire buf_empty;
wire buf_full;
wire [6:0] fifo_counter;

FIFO dut (
  .clk(clk),
  .rst(rst),
  .wr_en(wr_en),
  .rd_en(rd_en),
  .buf_in(buf_in),
  .buf_out(buf_out),
  .buf_empty(buf_empty),
  .buf_full(buf_full),
  .fifo_counter(fifo_counter)
);

// Clock generation
always #5 clk = ~clk;

initial begin
  clk = 0;
  rst = 1;
  wr_en = 0;
  rd_en = 0;
  buf_in = 0;

  // Reset
  #10 rst = 0;

  // Write data
  repeat (5) begin
    @(posedge clk);
    wr_en = 1;
    buf_in = buf_in + 8'd1;
  end

  @(posedge clk);
  wr_en = 0;

  // Read data
  repeat (5) begin
    @(posedge clk);
    rd_en = 1;
  end

  @(posedge clk);
  rd_en = 0;

  // Simultaneous read & write
  @(posedge clk);
  wr_en = 1;
  rd_en = 1;
  buf_in = 8'hAA;

  @(posedge clk);
  wr_en = 0;
  rd_en = 0;

  #20 $finish;
end


initial 
begin

$dumpfile("fifo_sim.vcd");
$dumpvars(0 , FIFO_tb);

end


endmodule

FIFO/fifo_sim.vcd
$date
	Fri Feb 06 19:01:31 2026
$end
$version
	Icarus Verilog
$end
$timescale
	1ps
$end
$scope module FIFO_tb $end
$var wire 7 ! fifo_counter [6:0] $end
$var wire 8 " buf_out [7:0] $end
$var wire 1 # buf_full $end
$var wire 1 $ buf_empty $end
$var reg 8 % buf_in [7:0] $end
$var reg 1 & clk $end
$var reg 1 ' rd_en $end
$var reg 1 ( rst $end
$var reg 1 ) wr_en $end
$scope module dut $end
$var wire 8 * buf_in [7:0] $end
$var wire 1 & clk $end
$var wire 1 ' rd_en $end
$var wire 1 ( rst $end
$var wire 1 ) wr_en $end
$var wire 1 # buf_full $end
$var wire 1 $ buf_empty $end
$var reg 8 + buf_out [7:0] $end
$var reg 7 , fifo_counter [6:0] $end
$var reg 6 - r_ptr [5:0] $end
$var reg 6 . w_ptr [5:0] $end
$upscope $end
$upscope $end
$enddefinitions $end
$comment Show the parameter values. $end
$dumpall
$end
#0
$dumpvars
b0 .
b0 -
b0 ,
b0 +
b0 *
0)
1(
0'
0&
b0 %
1$
0#
b0 "
b0 !
$end
#5000
1&
#10000
0&
0(
#15000
0$
b1 !
b1 ,
b1 .
b1 %
b1 *
1)
1&
#20000
0&
#25000
b10 .
b10 !
b10 ,
b10 %
b10 *
1&
#30000
0&
#35000
b11 !
b11 ,
b11 .
b11 %
b11 *
1&
#40000
0&
#45000
b100 .
b100 !
b100 ,
b100 %
b100 *
1&
#50000
0&
#55000
b101 !
b101 ,
b101 .
b101 %
b101 *
1&
#60000
0&
#65000
0)
1&
#70000
0&
#75000
b100 !
b100 ,
b1 "
b1 +
b1 -
1'
1&
#80000
0&
#85000
b10 -
b11 !
b11 ,
1&
#90000
0&
#95000
b10 !
b10 ,
b11 "
b11 +
b11 -
1&
#100000
0&
#105000
b100 -
b1 !
b1 ,
1&
#110000
0&
#115000
1$
b0 !
b0 ,
b101 "
b101 +
b101 -
1&
#120000
0&
#125000
0'
1&
#130000
0&
#135000
0$
b1 !
b1 ,
b110 .
b10101010 %
b10101010 *
1'
1)
1&
#140000
0&
#145000
0'
0)
1&
