MIPS32 Pipelined Processor/pipe_MIPS32.v
module pipe_MIPS32(clk1 , clk2);


input clk1 , clk2 ;   //TWo-phase clock

reg [31 : 0] PC , IF_ID_IR , IF_ID_NPC;
reg [31 : 0] ID_EX_IR , ID_EX_NPC , ID_EX_A , ID_EX_B , ID_EX_Imm;
reg [2:0] ID_EX_type , EX_MEM_type , MEM_WB_type;  //?
reg [31 :0] EX_MEM_IR , EX_MEM_ALUOut , EX_MEM_B;

reg EX_MEM_cond;

reg [31:0] MEM_WB_IR  , MEM_WB_ALUOut , MEM_WB_LMD;

reg [31:0] Reg [0:31];   //Register bank (32 x 32)

reg [31:0] Mem [0:1023];  //1024 x 32 memory   1024 words each of 32 bit

//6 bit opcodes to parameters

parameter ADD = 6'b000000 , SUB = 6'b000001 , AND = 6'b000010 , OR = 6'b000011 , 
SLT = 6'b000100 , MUL = 6'b000101 , HLT = 6'b111111 , LW = 6'b001000 , SW = 6'b001001 , ADDI=6'b001010 
, SUBI = 6'b001011 , SLTI = 6'b001100 , BNEQZ = 6'b001101 , BEQZ = 6'b001110;


// types
parameter RR_ALU = 3'b000 , RM_ALU = 3'b001  , LOAD = 3'b010 , STORE = 3'b011 , BRANCH = 3'b100 , HALT = 3'b101 ;


reg HALTED;
 // set after HLT instruction is completed (in WB stage)

reg TAKEN_BRANCH;
  // Required to disable instructions after branch
  
//reset all to avoid floating 
initial
begin
 PC = 0;
 HALTED = 0;
 TAKEN_BRANCH = 0;
end

// IF Stage

always @(posedge clk1)

if (HALTED == 0)
begin
 if( ( ( EX_MEM_IR[31:26] == BEQZ) && (EX_MEM_cond == 1)) || ((EX_MEM_IR[31:26] == BNEQZ)  && (EX_MEM_cond == 0)))

 begin
    IF_ID_IR <= #2 Mem[EX_MEM_ALUOut];
    TAKEN_BRANCH <= #2 1'b1 ;
    IF_ID_NPC <= #2 EX_MEM_ALUOut + 1;
    PC        <= #2 EX_MEM_ALUOut + 1;
  end 
else
  begin
    IF_ID_IR   <= #2 Mem[PC];
    IF_ID_NPC  <= #2 PC + 1;
    PC         <= #2 PC + 1;
   end
end



 // ID Stage

 always @(posedge clk2)    //ID Stage
   if(HALTED == 0)
   begin

     //are we accessing R0 ? then value of A will be 0 else read from rs
      if (IF_ID_IR[25:21] == 5'b00000)  ID_EX_A <= 0;
      else ID_EX_A   <=  #2 Reg[IF_ID_IR[25:21]];  //"rs"


      if (IF_ID_IR[20:16] == 5'b00000)  ID_EX_B <=0 ;
      else ID_EX_B   <= #2 Reg[IF_ID_IR[20:16]] ; // "rt"
    

    ID_EX_NPC   <= #2 IF_ID_NPC;
    ID_EX_IR    <= #2 IF_ID_IR;
    ID_EX_Imm   <= #2 {{16{IF_ID_IR[15]}} , {IF_ID_IR[15:0]}};     //?

                    // sign extended 16 times          //this 16 bit indicates offset



  //check opcode again

 // based on opcode set type


case (IF_ID_IR[31:26])
  ADD , SUB , AND , OR , SLT , MUL :  ID_EX_type <=  #2 RR_ALU;
  ADDI , SUBI , SLTI :                ID_EX_type <= #2 RM_ALU;
  LW :                                ID_EX_type <= #2 LOAD;
  SW :                                ID_EX_type <= #2 STORE;
  BNEQZ,BEQZ :                        ID_EX_type <= #2 BRANCH;
  HLT :                               ID_EX_type <= #2 HALT;
  default :                           ID_EX_type <= #2 HALT;

                                            // invalid opcode
 endcase
end



// EX Stage
always @(posedge clk1)
if(HALTED == 0)
begin
    EX_MEM_type <= #2 ID_EX_type;
    EX_MEM_IR   <= #2 ID_EX_IR;
    TAKEN_BRANCH <= #2 0;  

//reg to reg
    case (ID_EX_type)
    RR_ALU : begin
              case  (ID_EX_IR[31:26])   //"opcode"
                ADD : EX_MEM_ALUOut <= #2 ID_EX_A + ID_EX_B;
                SUB : EX_MEM_ALUOut <= #2 ID_EX_A -  ID_EX_B;
                AND : EX_MEM_ALUOut <= #2 ID_EX_A & ID_EX_B ;
                OR : EX_MEM_ALUOut <= #2 ID_EX_A | ID_EX_B;
                SLT : EX_MEM_ALUOut <= #2 ID_EX_A < ID_EX_B;
                MUL : EX_MEM_ALUOut <= #2 ID_EX_A * ID_EX_B;
                default: EX_MEM_ALUOut <= #2 32'hxxxxxxxx;
                endcase

             end

            
//regsiter to memory
RM_ALU : begin
        case (ID_EX_IR[31:26])  //opcode
           ADDI : EX_MEM_ALUOut <= #2 ID_EX_A + ID_EX_Imm ;

           SUBI : EX_MEM_ALUOut <= #2 ID_EX_A - ID_EX_Imm ;
           SLTI : EX_MEM_ALUOut <= #2 ID_EX_A < ID_EX_Imm ;
           default : EX_MEM_ALUOut <= #2 32'hxxxxxxxx ;
        endcase
       end 

 LOAD , STORE:
            begin
               EX_MEM_ALUOut <= #2 ID_EX_A + ID_EX_Imm ;
               EX_MEM_B <= #2 ID_EX_B;     //
            end

     BRANCH : begin
                EX_MEM_ALUOut <= #2 ID_EX_NPC + ID_EX_Imm;
                EX_MEM_cond <=   #2 (ID_EX_A == 0);

               end
     endcase
  end


//MEM Stage

always @(posedge clk2 )
begin
if(HALTED == 0)
begin
        MEM_WB_type <= #2 EX_MEM_type;
        MEM_WB_IR <= #2 EX_MEM_IR;

        case (EX_MEM_type)
        RR_ALU , RM_ALU:               //, is for  or 
                 MEM_WB_ALUOut <= #2 EX_MEM_ALUOut;

        LOAD : MEM_WB_LMD  <= #2 Mem[EX_MEM_ALUOut];

        STORE : if(TAKEN_BRANCH == 0)   //Disable write
                 Mem[EX_MEM_ALUOut] <= #2 EX_MEM_B ;

   endcase

  end
end


//WB Stage
always @(posedge clk1)

begin
    if(TAKEN_BRANCH == 0)  //disable write if branch TAKEN_BRANCH high
    case (MEM_WB_type)

    RR_ALU :  Reg[MEM_WB_IR[15:11]] <= #2 MEM_WB_ALUOut;  // "rd"
    RM_ALU :  Reg[MEM_WB_IR[20:16]]  <= #2 MEM_WB_ALUOut;  // "rt"

    LOAD : Reg[MEM_WB_IR[20:16]] <= #2 MEM_WB_LMD ;  




    HALT: HALTED <= #2 1'b1;
    endcase
end


endmodule

MIPS32 Pipelined Processor/test5_mips32.v
module test5_mips32;


reg clk1 , clk2;

integer k;

pipe_MIPS32 dut(.clk1(clk1) , .clk2(clk2));


initial 
begin

clk1 =0;
clk2 =0;

repeat(20)begin
 clk1 = #5 1'b1 ; clk2 = #5 1'b0 ;
 
 clk2 = #5 1'b1 ; clk1 = #5 1'b0 ;
end
end


initial begin
  // Initialize registers
  dut.Reg[1] = 5;   // base address
  dut.Reg[2] = 10;
  dut.Reg[4] = 10;

  // Initialize memory
  dut.Mem[5] = 20;  // data to load

  // Program
  dut.Mem[0] = 32'h20210000; // LW R1, 0(R1) (example encoding adjust)
  dut.Mem[1] = 32'h0ce77800;  // OR R7 , R7 , R7 -- dummy instruct
   
 // mips.Mem[2] = 32'h0ce77800;  // OR R7 , R7 , R7 -- dummy instruct
   
  dut.Mem[2] = 32'h00241800; // ADD R3, R1, R4

#100;


$display("R1 = %d " ,dut.Reg[1]);


$display("R2 = %d " ,dut.Reg[2]);

$display("R3 = %d " ,dut.Reg[3]);




end

initial
begin

$dumpfile("test5.vcd");
$dumpvars(0 , test5_mips32);

#100
$finish;

end




endmodule

MIPS32 Pipelined Processor/test5.vcd
$date
	Tue Apr 07 13:45:49 2026
$end
$version
	Icarus Verilog
$end
$timescale
	1s
$end
$scope module test5_mips32 $end
$var reg 1 ! clk1 $end
$var reg 1 " clk2 $end
$scope module dut $end
$var wire 1 ! clk1 $end
$var wire 1 " clk2 $end
$var parameter 6 # ADD $end
$var parameter 6 $ ADDI $end
$var parameter 6 % AND $end
$var parameter 6 & BEQZ $end
$var parameter 6 ' BNEQZ $end
$var parameter 3 ( BRANCH $end
$var parameter 3 ) HALT $end
$var parameter 6 * HLT $end
$var parameter 3 + LOAD $end
$var parameter 6 , LW $end
$var parameter 6 - MUL $end
$var parameter 6 . OR $end
$var parameter 3 / RM_ALU $end
$var parameter 3 0 RR_ALU $end
$var parameter 6 1 SLT $end
$var parameter 6 2 SLTI $end
$var parameter 3 3 STORE $end
$var parameter 6 4 SUB $end
$var parameter 6 5 SUBI $end
$var parameter 6 6 SW $end
$var reg 32 7 EX_MEM_ALUOut [31:0] $end
$var reg 32 8 EX_MEM_B [31:0] $end
$var reg 32 9 EX_MEM_IR [31:0] $end
$var reg 1 : EX_MEM_cond $end
$var reg 3 ; EX_MEM_type [2:0] $end
$var reg 1 < HALTED $end
$var reg 32 = ID_EX_A [31:0] $end
$var reg 32 > ID_EX_B [31:0] $end
$var reg 32 ? ID_EX_IR [31:0] $end
$var reg 32 @ ID_EX_Imm [31:0] $end
$var reg 32 A ID_EX_NPC [31:0] $end
$var reg 3 B ID_EX_type [2:0] $end
$var reg 32 C IF_ID_IR [31:0] $end
$var reg 32 D IF_ID_NPC [31:0] $end
$var reg 32 E MEM_WB_ALUOut [31:0] $end
$var reg 32 F MEM_WB_IR [31:0] $end
$var reg 32 G MEM_WB_LMD [31:0] $end
$var reg 3 H MEM_WB_type [2:0] $end
$var reg 32 I PC [31:0] $end
$var reg 1 J TAKEN_BRANCH $end
$upscope $end
$upscope $end
$enddefinitions $end
$comment Show the parameter values. $end
$dumpall
b1001 6
b1011 5
b1 4
b11 3
b1100 2
b100 1
b0 0
b1 /
b11 .
b101 -
b1000 ,
b10 +
b111111 *
b101 )
b100 (
b1101 '
b1110 &
b10 %
b1010 $
b0 #
$end
#0
$dumpvars
0J
b0 I
bx H
bx G
bx F
bx E
bx D
bx C
bx B
bx A
bx @
bx ?
bx >
bx =
0<
bx ;
x:
bx 9
bx 8
bx 7
0"
0!
$end
#5
1!
#7
b1 I
b1 D
b100000001000010000000000000000 C
#15
1"
#17
b10 B
b0 @
b100000001000010000000000000000 ?
b1 A
b101 >
b101 =
#20
0!
#25
1!
#27
b101 8
b101 7
b100000001000010000000000000000 9
b10 ;
b10 I
b10 D
b1100111001110111100000000000 C
#30
0"
#35
1"
#37
b10100 G
b100000001000010000000000000000 F
b10 H
b0 B
b111100000000000 @
b1100111001110111100000000000 ?
b10 A
bx >
bx =
#40
0!
#45
1!
#47
b11 I
b11 D
b1001000001100000000000 C
bx 7
b1100111001110111100000000000 9
b0 ;
#50
0"
#55
1"
#57
b1100000000000 @
b1001000001100000000000 ?
b11 A
b1010 >
b10100 =
b1100111001110111100000000000 F
b0 H
#60
0!
#65
1!
#67
b11110 7
b1001000001100000000000 9
b100 I
b100 D
bx C
#70
0"
#75
1"
#77
b11110 E
b1001000001100000000000 F
b101 B
bx @
bx ?
b100 A
bx >
bx =
#80
0!
#85
1!
#87
b101 I
b101 D
bx 9
b101 ;
#90
0"
#95
1"
#97
b101 A
bx F
b101 H
