fir_filter_dac_verilog/dac_interface.v
`timescale 1ns / 1ps

// ----------------------------------------------------------------------
// 1. DAC Interface Module (DAC084S085 Driver)
//    - Implements the 16-bit serial protocol for the 4-channel, 8-bit DAC.
//    - Assumes the DAC expects a 16-bit frame: 4 control bits (Channel Address) + 8 Data bits + 4 Don't Care bits.
// ----------------------------------------------------------------------

module dac_interface (
    input clk,            // System clock (12 MHz)
    input RST,            // Synchronous Reset
    input signed [31:0] fir_output, // 32-bit signed output from the FIR filter

    // DAC Control Signal Outputs (Connect to physical FPGA pins)
    output reg dac_clk,   // P70 (SCLK) - Serial Clock
    output reg dac_cs,    // P100 (CS)  - Chip Select
    output reg dac_din    // P65 (DIN)  - Serial Data Input
);

    // --- Parameters and Constants ---
    localparam FRAME_SIZE = 16;
    localparam CHANNEL_A = 4'b0000; // Channel A (OUT-A) for the filtered signal

    // --- State Machine Registers ---
    reg [4:0] bit_counter;        // Counter for the 16 bits in the frame (0 to 15)
    reg [FRAME_SIZE - 1: 0] shift_register; // Holds the 16-bit data frame to be sent

    // --- Scaled and Biased Data Conversion ---
    // FIR output is 32-bit signed. DAC is 8-bit unipolar (0 to 255).
    // Right shift by 16 bits is used for scaling (discarding the 16 LSBs).
    wire signed [7:0] scaled_out_signed;
    // Arithmetic right shift by 16
    assign scaled_out_signed = fir_output[31:0] >>> 16; 

    // Convert signed [-128, 127] to unsigned [0, 255] by adding DC bias (128).
    wire [7:0] dac_data_value = scaled_out_signed + 8'd128;

    // --- Main Clock and State Control ---
    // CLK = 12 MHz. We target a dac_clk (SCLK) frequency around 750 kHz.
    // We use a clock divider to generate a slower clock for the serial state machine.
    // The state machine clock (slow_clk) will run at CLK / 8 = 1.5 MHz.
    // The dac_clk (SCLK) runs at half this speed (toggled in the always block) = 750 kHz.
    reg [2:0] clk_divider_reg = 0; // 3-bit counter for CLK/8 division
    wire slow_clk;

    // Generate a pulse every 8 system clocks (1.5 MHz)
    always @(posedge clk) begin
        clk_divider_reg <= clk_divider_reg + 1'b1;
    end
    assign slow_clk = clk_divider_reg[2]; // CLK/8

    // --- Data Loading and Shifting Logic (FSM) ---

    always @(posedge slow_clk) begin
        if (RST) begin
            bit_counter <= 0;
            dac_cs <= 1'b1; // Chip Select is high (inactive)
            dac_clk <= 1'b0;
            dac_din <= 1'b0;
            shift_register <= 0;
        end else begin
            // 1. DAC Clock Generation (SCLK)
            // Toggles on every 'slow_clk' edge, running at 750 kHz.
            dac_clk <= ~dac_clk;

            // 2. Main State Logic (Triggered on positive edge of the slower dac_clk)
            // Note: We use 'if (dac_clk)' to ensure data changes on the DAC's falling edge
            // and is sampled on the rising edge, or vice-versa, depending on DAC clock polarity.
            // This setup uses the rising edge of dac_clk for shifting control.
            if (dac_clk) begin
                if (bit_counter == 0) begin
                    // --- START OF FRAME: Load Data and Assert CS ---
                    dac_cs <= 1'b0; // Chip Select low (active)

                    // 16-bit frame format: [4 Control Bits | 8 Data Bits | 4 Don't Care Bits]
                    shift_register <= {CHANNEL_A, dac_data_value, 4'b0000};
                    bit_counter <= bit_counter + 1;
                end else if (bit_counter < FRAME_SIZE) begin
                    // --- SHIFTING PHASE: Send one bit of data ---
                    dac_din <= shift_register[FRAME_SIZE - 1]; // Output MSB of the frame
                    shift_register <= shift_register << 1;     // Shift the register left
                    bit_counter <= bit_counter + 1;
                end else begin
                    // --- END OF FRAME: De-assert CS ---
                    dac_cs <= 1'b1; // Chip Select high (inactive)
                    bit_counter <= 0; // Reset counter
                    dac_din <= 1'b0;
                end
            end
        end
    end

endmodule // dac_interface

// The top_fir_dac module remains unchanged as it simply connects the two main blocks.

fir_filter_dac_verilog/fir_filter.v
//
//
//
//
//


`timescale 1ns / 1 ps

module fir_filter (input_data , clk , RST , ENABLE , output_data , sampleT);
//  FIR coefficient word width
parameter N1 = 8;
// input data word width
parameter N2 = 16;

//output data word witdh
parameter N3 = 32; // to be safe side
//here the number of bits representing output is larger than that of the output 
// this is mainly because the after every multiplication or additional binary number results will have
// increase no of binary bits to representing accurately the result
//hence bit size grows
//generally we need more no of bits than that of to store bits variables that particate in multiplication
//you can do simulation to check no of bits

//this array is used to store the coefficients

wire signed [N1 -1 : 0] b[0:7];
//this array is declared as array even if filter coefficient may be positive
//but inputs can be -ve
//whenever you have your in or out -ve use signed

// filter coefficients


assign b[0] = 8'b00010000;
assign b[1] = 8'b00010000;
assign b[2] = 8'b00010000;
assign b[3] = 8'b00010000;
assign b[4] = 8'b00010000;
assign b[5] = 8'b00010000;
assign b[6] = 8'b00010000;
assign b[7] = 8'b00010000;

 
 //input data

 input signed [N2 - 1 : 0] input_data;

 //output data samples

 output signed [N2-1 : 0] sampleT;

 //clock
 input clk;

//used to set to zero all filter taps
input RST;

//used to enable the filter
input ENABLE;
//filtered data

output signed [N3-1 : 0] output_data;


//this register is used to store the output
reg signed [N3-1 : 0] output_data_reg ;

//this array is used to store samples and to shift them
reg signed [N2-1:0] samples[0:6];
// 7 past input values
//uk uk-1 uk-2

always @(posedge clk)
begin
if (RST)
begin

samples[0] <= 0;
samples[1] <= 0; //all the statements are excecuted at the same time 
samples[2] <= 0; //imediatly after positive edge clock
samples[3] <= 0; //setting  all the past values of sample to 0
samples[4] <= 0; //
samples[5] <= 0;
samples[6] <= 0;
output_data_reg <=0; //output of value to be 0
end
 
 if((ENABLE == 1'b1) && (RST == 1'b0))
 begin
 output_data_reg <= b[0]*input_data 
                     + b[1]*samples[0]
                     + b[2]*samples[1]
                     + b[3]*samples[2]
                     + b[4]*samples[3]
                     + b[5]*samples[4]
                     + b[6]*samples[5]
                     + b[7]*samples[6];


        samples[0]  <= input_data;
        samples[1] <= samples[0];
        samples[2] <= samples[1];
        samples[3] <= samples[2];
        samples[4] <= samples[3];
        samples[5] <= samples[4];
        samples[6] <= samples[5];
        //we need to store input values  that is we need to properly assign
        // pass input values  
    end
end

 assign output_data = output_data_reg;
 assign sampleT = samples[0]; 
 //you can select any sample and can inspect it later on in our simulation
 //time diagram


endmodule

fir_filter_dac_verilog/top_fir_dac.v
`timescale 1ns / 1ps

// This module connects the FIR filter output to the DAC interface input.
module top_fir_dac (
    // System Ports (Input from FPGA)
    input clk,
    input RST,
    input ENABLE,
    input signed [15:0] input_data,

    // DAC Output Pins (To be connected to P70, P100, P65)
    output dac_clk_pin,   
    output dac_cs_pin,    
    output dac_din_pin,   

    // Debug Output (for Testbench and FPGA Debug)
    output signed [31:0] fir_out_debug
);

    // Internal wire to carry the 32-bit filtered output
    wire signed [31:0] fir_output_data;
    
    // Unused wire from the FIR filter (sampleT is 16-bit)
    wire signed [15:0] sampleT_unused; 

    // 1. Instantiate the FIR Filter Module (Assumes fir_filter.v exists)
    fir_filter fir_inst (
        .input_data  (input_data),
        .clk         (clk),
        .RST         (RST),
        .ENABLE      (ENABLE),
        .output_data (fir_output_data),
        .sampleT     (sampleT_unused)
    );

    // Assign debug output
    assign fir_out_debug = fir_output_data;

    // 2. Instantiate the DAC Interface Module (Assumes dac_interface.v exists)
    dac_interface dac_inst (
        .clk         (clk),
        .RST         (RST),
        .fir_output  (fir_output_data), // Connect filter output to DAC input

        // Connect DAC interface outputs to top-level pins
        .dac_clk     (dac_clk_pin),
        .dac_cs      (dac_cs_pin),
        .dac_din     (dac_din_pin)
    );

endmodule // top_fir_dac

fir_filter_dac_verilog/fir_dac_tb.v
`timescale 1ns / 1ps

module fir_dac_tb;

    // --- Simulation Parameters ---
    parameter CLK_PERIOD = 83.333; // 12 MHz clock period (1/12M = 83.333 ns)

    // --- Inputs to the DUT (top_fir_dac) ---
    reg clk;
    reg RST;
    reg ENABLE;
    reg signed [15:0] input_data;

    // --- Outputs from the DUT ---
    // DAC Pins (P70, P100, P65)
    wire dac_clk_pin;
    wire dac_cs_pin;
    wire dac_din_pin;

    // FIR Debug Output (32-bit result before scaling)
    wire signed [31:0] fir_out_debug;

    // --- Internal Memory and Control ---
    // NOTE: N2 is 16 from the original file, using 15:0 for signed input
    reg [15:0] data[99:0]; 
    integer k;
    integer FILE1;

    // --- Instantiate the DUT (Top Module) ---
    // The top_fir_dac module internally instantiates fir_filter and dac_interface.
    top_fir_dac UUT (
        .clk(clk),
        .RST(RST),
        .ENABLE(ENABLE),
        .input_data(input_data),
        .dac_clk_pin(dac_clk_pin),
        .dac_cs_pin(dac_cs_pin),
        .dac_din_pin(dac_din_pin),
        .fir_out_debug(fir_out_debug)
    );

    // --- 1. Clock Generation (12 MHz) ---
    // Half period is ~41.666 ns
    always # (CLK_PERIOD / 2.0) clk = ~clk;

    // --- 2. Stimulus Generation ---
    initial begin
        // Load input samples from file
        $readmemb("input.data" , data);

        // Open file for saving the filtered data
        FILE1 = $fopen("filtered_output.data" , "w");

        // Initialization
        clk = 1'b0;
        RST = 1'b1;
        ENABLE = 1'b0;
        input_data = 16'd0;

        $display("----------------------------------------------");
        $display("Starting FIR/DAC Simulation (12 MHz CLK)");
        $display("----------------------------------------------");

        // 1. Assert Reset
        # (CLK_PERIOD * 5); 
        RST = 1'b0;

        // 2. Enable Filter and Start Data Feed
        ENABLE = 1'b1;
        input_data <= data[0]; // Load first sample

        // Loop to feed 99 subsequent samples and capture output
        for(k = 1 ; k < 100 ; k=k+1) begin
            @(posedge clk);
            
            // Capture FIR output (32-bit) before it is sent to the DAC
            $fdisplay(FILE1 , "%b" , fir_out_debug);

            // Feed the next input sample
            input_data <= data[k];

            if(k == 99) begin
                // Wait for one more clock cycle to capture the last output
                @(posedge clk); 
                $fdisplay(FILE1 , "%b" , fir_out_debug);
                $fclose(FILE1);
            end
        end
         
        // 3. Wait to observe multiple DAC cycles after all data is processed
        // DAC clock period is 1/750kHz = 1333 ns.
        // A single 16-bit frame takes 16 * 1333 ns = ~21.3 us.
        // Waiting for 100 * CLK_PERIOD (~8.3 us) is enough to see a few transmissions.
        # (CLK_PERIOD * 100); 

        $display("----------------------------------------------");
        $display("Simulation Finished. Data saved to filtered_output.data");
        $display("----------------------------------------------");
        $stop;
    end
    
    // --- 3. DAC Pin Monitoring ---
    always @(negedge dac_cs_pin) begin
        $display("@ %t: DAC Start. FIR Output (32-bit): 0x%h", $time, fir_out_debug);
    end
    
    always @(posedge dac_cs_pin) begin
        $display("@ %t: DAC End. Waiting for next cycle.", $time);
    end


initial
begin
$dumpfile("top.vcd");
$dumpvars( 0 , fir_dac_tb);
end

endmodule

fir_filter_dac_verilog/top.vcd
$date
	Sat Dec 06 22:12:56 2025
$end
$version
	Icarus Verilog
$end
$timescale
	1ps
$end
$scope module fir_dac_tb $end
$var wire 32 ! fir_out_debug [31:0] $end
$var wire 1 " dac_din_pin $end
$var wire 1 # dac_cs_pin $end
$var wire 1 $ dac_clk_pin $end
$var real 1 % CLK_PERIOD $end
$var reg 1 & ENABLE $end
$var reg 1 ' RST $end
$var reg 1 ( clk $end
$var reg 16 ) input_data [15:0] $end
$var integer 32 * FILE1 [31:0] $end
$var integer 32 + k [31:0] $end
$scope module UUT $end
$var wire 1 & ENABLE $end
$var wire 1 ' RST $end
$var wire 1 ( clk $end
$var wire 32 , fir_out_debug [31:0] $end
$var wire 16 - input_data [15:0] $end
$var wire 16 . sampleT_unused [15:0] $end
$var wire 32 / fir_output_data [31:0] $end
$var wire 1 " dac_din_pin $end
$var wire 1 # dac_cs_pin $end
$var wire 1 $ dac_clk_pin $end
$scope module dac_inst $end
$var wire 1 ' RST $end
$var wire 1 ( clk $end
$var wire 1 0 slow_clk $end
$var wire 8 1 scaled_out_signed [7:0] $end
$var wire 32 2 fir_output [31:0] $end
$var wire 8 3 dac_data_value [7:0] $end
$var parameter 4 4 CHANNEL_A $end
$var parameter 32 5 FRAME_SIZE $end
$var reg 5 6 bit_counter [4:0] $end
$var reg 3 7 clk_divider_reg [2:0] $end
$var reg 1 $ dac_clk $end
$var reg 1 # dac_cs $end
$var reg 1 " dac_din $end
$var reg 16 8 shift_register [15:0] $end
$upscope $end
$scope module fir_inst $end
$var wire 1 & ENABLE $end
$var wire 1 ' RST $end
$var wire 1 ( clk $end
$var wire 16 9 input_data [15:0] $end
$var wire 16 : sampleT [15:0] $end
$var wire 32 ; output_data [31:0] $end
$var parameter 32 < N1 $end
$var parameter 32 = N2 $end
$var parameter 32 > N3 $end
$var reg 32 ? output_data_reg [31:0] $end
$upscope $end
$upscope $end
$upscope $end
$enddefinitions $end
$comment Show the parameter values. $end
$dumpall
b100000 >
b10000 =
b1000 <
b10000 5
b0 4
r83.333 %
$end
#0
$dumpvars
bx ?
bx ;
bx :
b0 9
bx 8
b0 7
bx 6
bx 3
bx 2
bx 1
00
bx /
bx .
b0 -
bx ,
bx +
b10000000000000000000000000000011 *
b0 )
0(
1'
0&
x$
x#
x"
bx !
$end
#41667
b10000000 3
b0 1
b0 !
b0 ,
b0 /
b0 2
b0 ;
b0 ?
b0 .
b0 :
b1 7
1(
#83334
0(
#125001
b10 7
1(
#166668
0(
#208335
b11 7
1(
#250002
0(
#291669
b0 8
0"
0$
1#
b0 6
10
b100 7
1(
#333336
0(
#375003
b101 7
1(
#416665
b1100000 )
b1100000 -
b1100000 9
b1 +
1&
0'
#416670
0(
#458337
b110 7
b1100000 .
b1100000 :
b11000000000 !
b11000000000 ,
b11000000000 /
b11000000000 2
b11000000000 ;
b11000000000 ?
b10010010 )
b10010010 -
b10010010 9
b10 +
1(
#500004
0(
#541671
b1000000 )
b1000000 -
b1000000 9
b10010010 .
b10010010 :
b111100100000 !
b111100100000 ,
b111100100000 /
b111100100000 2
b111100100000 ;
b111100100000 ?
b111 7
b11 +
1(
#583338
0(
#625005
00
b0 7
b1000000 .
b1000000 :
b1001100100000 !
b1001100100000 ,
b1001100100000 /
b1001100100000 2
b1001100100000 ;
b1001100100000 ?
b10101000 )
b10101000 -
b10101000 9
b100 +
1(
#666672
0(
#708339
b10001010 )
b10001010 -
b10001010 9
b10101000 .
b10101000 :
b1110110100000 !
b1110110100000 ,
b1110110100000 /
b1110110100000 2
b1110110100000 ;
b1110110100000 ?
b1 7
b101 +
1(
#750006
0(
#791673
b10 7
b10001010 .
b10001010 :
b10011001000000 !
b10011001000000 ,
b10011001000000 /
b10011001000000 2
b10011001000000 ;
b10011001000000 ?
b10001101 )
b10001101 -
b10001101 9
b110 +
1(
#833340
0(
#875007
b10111011 )
b10111011 -
b10111011 9
b10001101 .
b10001101 :
b10111100010000 !
b10111100010000 ,
b10111100010000 /
b10111100010000 2
b10111100010000 ;
b10111100010000 ?
b11 7
b111 +
1(
#916674
0(
#958341
1$
10
b100 7
b10111011 .
b10111011 :
b11101011000000 !
b11101011000000 ,
b11101011000000 /
b11101011000000 2
b11101011000000 ;
b11101011000000 ?
b1011101 )
b1011101 -
b1011101 9
b1000 +
1(
#1000008
0(
#1041675
b1010101 )
b1010101 -
b1010101 9
b1011101 .
b1011101 :
b100000010010000 !
b100000010010000 ,
b100000010010000 /
b100000010010000 2
b100000010010000 ;
b100000010010000 ?
b101 7
b1001 +
1(
#1083342
0(
#1125009
b110 7
b1010101 .
b1010101 :
b11111111100000 !
b11111111100000 ,
b11111111100000 /
b11111111100000 2
b11111111100000 ;
b11111111100000 ?
b10000110 )
b10000110 -
b10000110 9
b1010 +
1(
#1166676
0(
#1208343
b10001011 )
b10001011 -
b10001011 9
b10000110 .
b10000110 :
b11111100100000 !
b11111100100000 ,
b11111100100000 /
b11111100100000 2
b11111100100000 ;
b11111100100000 ?
b111 7
b1011 +
1(
#1250010
0(
#1291677
00
b0 7
b10001011 .
b10001011 :
b100001111010000 !
b100001111010000 ,
b100001111010000 /
b100001111010000 2
b100001111010000 ;
b100001111010000 ?
b10010100 )
b10010100 -
b10010100 9
b1100 +
1(
#1333344
0(
#1375011
b1001000 )
b1001000 -
b1001000 9
b10010100 .
b10010100 :
b100001010010000 !
b100001010010000 ,
b100001010010000 /
b100001010010000 2
b100001010010000 ;
b100001010010000 ?
b1 7
b1101 +
1(
#1416678
0(
#1458345
b10 7
b1001000 .
b1001000 :
b11111001110000 !
b11111001110000 ,
b11111001110000 /
b11111001110000 2
b11111001110000 ;
b11111001110000 ?
b10001 )
b10001 -
b10001 9
b1110 +
1(
#1500012
0(
#1541679
b1111111110101011 )
b1111111110101011 -
b1111111110101011 9
b10001 .
b10001 :
b11011010110000 !
b11011010110000 ,
b11011010110000 /
b11011010110000 2
b11011010110000 ;
b11011010110000 ?
b11 7
b1111 +
1(
#1583346
0(
#1625013
b1 6
b100000000000 8
0#
0$
10
b100 7
b1111111110101011 .
b1111111110101011 :
b10010110110000 !
b10010110110000 ,
b10010110110000 /
b10010110110000 2
b10010110110000 ;
b10010110110000 ?
b1111111111100100 )
b1111111111100100 -
b1111111111100100 9
b10000 +
1(
#1666680
0(
#1708347
b1111111111001000 )
b1111111111001000 -
b1111111111001000 9
b1111111111100100 .
b1111111111100100 :
b1111000100000 !
b1111000100000 ,
b1111000100000 /
b1111000100000 2
b1111000100000 ;
b1111000100000 ?
b101 7
b10001 +
1(
#1750014
0(
#1791681
b110 7
b1111111111001000 .
b1111111111001000 :
b1010101010000 !
b1010101010000 ,
b1010101010000 /
b1010101010000 2
b1010101010000 ;
b1010101010000 ?
b1111111110100110 )
b1111111110100110 -
b1111111110100110 9
b10010 +
1(
#1833348
0(
#1875015
b101001 )
b101001 -
b101001 9
b1111111110100110 .
b1111111110100110 :
b11101010000 !
b11101010000 ,
b11101010000 /
b11101010000 2
b11101010000 ;
b11101010000 ?
b111 7
b10011 +
1(
#1916682
0(
#1958349
00
b0 7
b101001 .
b101001 :
b100110000 !
b100110000 ,
b100110000 /
b100110000 2
b100110000 ;
b100110000 ?
b1 )
b1 -
b1 9
b10100 +
1(
#2000016
0(
#2041683
b1111111 3
b11111111 1
b1111111110101101 )
b1111111110101101 -
b1111111110101101 9
b1 .
b1 :
b11111111111111111111100000000000 !
b11111111111111111111100000000000 ,
b11111111111111111111100000000000 /
b11111111111111111111100000000000 2
b11111111111111111111100000000000 ;
b11111111111111111111100000000000 ?
b1 7
b10101 +
1(
#2083350
0(
#2125017
b10 7
b1111111110101101 .
b1111111110101101 :
b11111111111111111110111001010000 !
b11111111111111111110111001010000 ,
b11111111111111111110111001010000 /
b11111111111111111110111001010000 2
b11111111111111111110111001010000 ;
b11111111111111111110111001010000 ?
b1111111111111010 )
b1111111111111010 -
b1111111111111010 9
b10110 +
1(
#2166684
0(
#2208351
b100011 )
b100011 -
b100011 9
b1111111111111010 .
b1111111111111010 :
b11111111111111111110110011100000 !
b11111111111111111110110011100000 ,
b11111111111111111110110011100000 /
b11111111111111111110110011100000 2
b11111111111111111110110011100000 ;
b11111111111111111110110011100000 ?
b11 7
b10111 +
1(
#2250018
0(
#2291685
1$
10
b100 7
b100011 .
b100011 :
b11111111111111111111010001100000 !
b11111111111111111111010001100000 ,
b11111111111111111111010001100000 /
b11111111111111111111010001100000 2
b11111111111111111111010001100000 ;
b11111111111111111111010001100000 ?
b1111111111111100 )
b1111111111111100 -
b1111111111111100 9
b11000 +
1(
#2333352
0(
#2375019
b1111111111000010 )
b1111111111000010 -
b1111111111000010 9
b1111111111111100 .
b1111111111111100 :
b11111111111111111111010111100000 !
b11111111111111111111010111100000 ,
b11111111111111111111010111100000 /
b11111111111111111111010111100000 2
b11111111111111111111010111100000 ;
b11111111111111111111010111100000 ?
b101 7
b11001 +
1(
#2416686
0(
#2458353
b110 7
b1111111111000010 .
b1111111111000010 :
b11111111111111111111010110000000 !
b11111111111111111111010110000000 ,
b11111111111111111111010110000000 /
b11111111111111111111010110000000 2
b11111111111111111111010110000000 ;
b11111111111111111111010110000000 ?
b110010 )
b110010 -
b110010 9
b11010 +
1(
#2500020
0(
#2541687
b11101 )
b11101 -
b11101 9
b110010 .
b110010 :
b11111111111111111111111001000000 !
b11111111111111111111111001000000 ,
b11111111111111111111111001000000 /
b11111111111111111111111001000000 2
b11111111111111111111111001000000 ;
b11111111111111111111111001000000 ?
b111 7
b11011 +
1(
#2583354
0(
#2625021
00
b0 7
b11101 .
b11101 :
b11111111111111111111110110000000 !
b11111111111111111111110110000000 ,
b11111111111111111111110110000000 /
b11111111111111111111110110000000 2
b11111111111111111111110110000000 ;
b11111111111111111111110110000000 ?
b1111111111110111 )
b1111111111110111 -
b1111111111110111 9
b11100 +
1(
#2666688
0(
#2708355
b1111111111111010 )
b1111111111111010 -
b1111111111111010 9
b1111111111110111 .
b1111111111110111 :
b11111111111111111111110011100000 !
b11111111111111111111110011100000 ,
b11111111111111111111110011100000 /
b11111111111111111111110011100000 2
b11111111111111111111110011100000 ;
b11111111111111111111110011100000 ?
b1 7
b11101 +
1(
#2750022
0(
#2791689
b10000000 3
b0 1
b10 7
b1111111111111010 .
b1111111111111010 :
b110110000 !
b110110000 ,
b110110000 /
b110110000 2
b110110000 ;
b110110000 ?
b1111111111110100 )
b1111111111110100 -
b1111111111110100 9
b11110 +
1(
#2833356
0(
#2875023
b1111 )
b1111 -
b1111 9
b1111111111110100 .
b1111111111110100 :
b101010000 !
b101010000 ,
b101010000 /
b101010000 2
b101010000 ;
b101010000 ?
b11 7
b11111 +
1(
#2916690
0(
#2958357
b10 6
b1000000000000 8
0$
10
b100 7
b1111 .
b1111 :
b10000 !
b10000 ,
b10000 /
b10000 2
b10000 ;
b10000 ?
b0 )
b0 -
b0 9
b100000 +
1(
#3000024
0(
#3041691
b101100 )
b101100 -
b101100 9
b0 .
b0 :
b1010000 !
b1010000 ,
b1010000 /
b1010000 2
b1010000 ;
b1010000 ?
b101 7
b100001 +
1(
#3083358
0(
#3125025
b110 7
b101100 .
b101100 :
b11011110000 !
b11011110000 ,
b11011110000 /
b11011110000 2
b11011110000 ;
b11011110000 ?
b1111111111001011 )
b1111111111001011 -
b1111111111001011 9
b100010 +
1(
#3166692
0(
#3208359
b0 )
b0 -
b0 9
b1111111111001011 .
b1111111111001011 :
b10000000 !
b10000000 ,
b10000000 /
b10000000 2
b10000000 ;
b10000000 ?
b111 7
b100011 +
1(
#3250026
0(
#3291693
b1111111 3
b11111111 1
00
b0 7
b0 .
b0 :
b11111111111111111111111010110000 !
b11111111111111111111111010110000 ,
b11111111111111111111111010110000 /
b11111111111111111111111010110000 2
b11111111111111111111111010110000 ;
b11111111111111111111111010110000 ?
b11100 )
b11100 -
b11100 9
b100100 +
1(
#3333360
0(
#3375027
b10000000 3
b0 1
b10001 )
b10001 -
b10001 9
b11100 .
b11100 :
b100000000 !
b100000000 ,
b100000000 /
b100000000 2
b100000000 ;
b100000000 ?
b1 7
b100101 +
1(
#3416694
0(
#3458361
b10 7
b10001 .
b10001 :
b1001110000 !
b1001110000 ,
b1001110000 /
b1001110000 2
b1001110000 ;
b1001110000 ?
b1111111110110011 )
b1111111110110011 -
b1111111110110011 9
b100110 +
1(
#3500028
0(
#3541695
b1111111 3
b11111111 1
b1111111111101010 )
b1111111111101010 -
b1111111111101010 9
b1111111110110011 .
b1111111110110011 :
b11111111111111111111111001100000 !
b11111111111111111111111001100000 ,
b11111111111111111111111001100000 /
b11111111111111111111111001100000 2
b11111111111111111111111001100000 ;
b11111111111111111111111001100000 ?
b11 7
b100111 +
1(
#3583362
0(
#3625029
1$
10
b100 7
b1111111111101010 .
b1111111111101010 :
b11111111111111111111110000010000 !
b11111111111111111111110000010000 ,
b11111111111111111111110000010000 /
b11111111111111111111110000010000 2
b11111111111111111111110000010000 ;
b11111111111111111111110000010000 ?
b1111111110010011 )
b1111111110010011 -
b1111111110010011 9
b101000 +
1(
#3666696
0(
#3708363
b1111111101001100 )
b1111111101001100 -
b1111111101001100 9
b1111111110010011 .
b1111111110010011 :
b11111111111111111111010101000000 !
b11111111111111111111010101000000 ,
b11111111111111111111010101000000 /
b11111111111111111111010101000000 2
b11111111111111111111010101000000 ;
b11111111111111111111010101000000 ?
b101 7
b101001 +
1(
#3750030
0(
#3791697
b110 7
b1111111101001100 .
b1111111101001100 :
b11111111111111111110011101000000 !
b11111111111111111110011101000000 ,
b11111111111111111110011101000000 /
b11111111111111111110011101000000 2
b11111111111111111110011101000000 ;
b11111111111111111110011101000000 ?
b1111111110011111 )
b1111111110011111 -
b1111111110011111 9
b101010 +
1(
#3833364
0(
#3875031
b1111111110011111 .
b1111111110011111 :
b11111111111111111110010010000000 !
b11111111111111111110010010000000 ,
b11111111111111111110010010000000 /
b11111111111111111110010010000000 2
b11111111111111111110010010000000 ;
b11111111111111111110010010000000 ?
b111 7
b101011 +
1(
#3916698
0(
#3958365
00
b0 7
b11111111111111111101111001110000 !
b11111111111111111101111001110000 ,
b11111111111111111101111001110000 /
b11111111111111111101111001110000 2
b11111111111111111101111001110000 ;
b11111111111111111101111001110000 ?
b1111111110101111 )
b1111111110101111 -
b1111111110101111 9
b101100 +
1(
#4000032
0(
#4041699
b1111111101001100 )
b1111111101001100 -
b1111111101001100 9
b1111111110101111 .
b1111111110101111 :
b11111111111111111101011110100000 !
b11111111111111111101011110100000 ,
b11111111111111111101011110100000 /
b11111111111111111101011110100000 2
b11111111111111111101011110100000 ;
b11111111111111111101011110100000 ?
b1 7
b101101 +
1(
#4083366
0(
#4125033
b10 7
b1111111101001100 .
b1111111101001100 :
b11111111111111111100101101010000 !
b11111111111111111100101101010000 ,
b11111111111111111100101101010000 /
b11111111111111111100101101010000 2
b11111111111111111100101101010000 ;
b11111111111111111100101101010000 ?
b1111111011111000 )
b1111111011111000 -
b1111111011111000 9
b101110 +
1(
#4166700
0(
#4208367
b1111111101010111 )
b1111111101010111 -
b1111111101010111 9
b1111111011111000 .
b1111111011111000 :
b11111111111111111011111110100000 !
b11111111111111111011111110100000 ,
b11111111111111111011111110100000 /
b11111111111111111011111110100000 2
b11111111111111111011111110100000 ;
b11111111111111111011111110100000 ?
b11 7
b101111 +
1(
#4250034
0(
#4291701
b11 6
b10000000000000 8
0$
10
b100 7
b1111111101010111 .
b1111111101010111 :
b11111111111111111011011001110000 !
b11111111111111111011011001110000 ,
b11111111111111111011011001110000 /
b11111111111111111011011001110000 2
b11111111111111111011011001110000 ;
b11111111111111111011011001110000 ?
b1111111110000100 )
b1111111110000100 -
b1111111110000100 9
b110000 +
1(
#4333368
0(
#4375035
b1111111110001110 )
b1111111110001110 -
b1111111110001110 9
b1111111110000100 .
b1111111110000100 :
b11111111111111111011010110000000 !
b11111111111111111011010110000000 ,
b11111111111111111011010110000000 /
b11111111111111111011010110000000 2
b11111111111111111011010110000000 ;
b11111111111111111011010110000000 ?
b101 7
b110001 +
1(
#4416702
0(
#4458369
b110 7
b1111111110001110 .
b1111111110001110 :
b11111111111111111011100110100000 !
b11111111111111111011100110100000 ,
b11111111111111111011100110100000 /
b11111111111111111011100110100000 2
b11111111111111111011100110100000 ;
b11111111111111111011100110100000 ?
b1111111110101100 )
b1111111110101100 -
b1111111110101100 9
b110010 +
1(
#4500036
0(
#4541703
b1111111101110111 )
b1111111101110111 -
b1111111101110111 9
b1111111110101100 .
b1111111110101100 :
b11111111111111111011101001110000 !
b11111111111111111011101001110000 ,
b11111111111111111011101001110000 /
b11111111111111111011101001110000 2
b11111111111111111011101001110000 ;
b11111111111111111011101001110000 ?
b111 7
b110011 +
1(
#4583370
0(
#4625037
00
b0 7
b1111111101110111 .
b1111111101110111 :
b11111111111111111011011111110000 !
b11111111111111111011011111110000 ,
b11111111111111111011011111110000 /
b11111111111111111011011111110000 2
b11111111111111111011011111110000 ;
b11111111111111111011011111110000 ?
b1111111110111001 )
b1111111110111001 -
b1111111110111001 9
b110100 +
1(
#4666704
0(
#4708371
b1111111110011010 )
b1111111110011010 -
b1111111110011010 9
b1111111110111001 .
b1111111110111001 :
b11111111111111111011100010010000 !
b11111111111111111011100010010000 ,
b11111111111111111011100010010000 /
b11111111111111111011100010010000 2
b11111111111111111011100010010000 ;
b11111111111111111011100010010000 ?
b1 7
b110101 +
1(
#4750038
0(
#4791705
b10 7
b1111111110011010 .
b1111111110011010 :
b11111111111111111011110101110000 !
b11111111111111111011110101110000 ,
b11111111111111111011110101110000 /
b11111111111111111011110101110000 2
b11111111111111111011110101110000 ;
b11111111111111111011110101110000 ?
b1111111110100101 )
b1111111110100101 -
b1111111110100101 9
b110110 +
1(
#4833372
0(
#4875039
b1111111111010101 )
b1111111111010101 -
b1111111111010101 9
b1111111110100101 .
b1111111110100101 :
b11111111111111111100100001000000 !
b11111111111111111100100001000000 ,
b11111111111111111100100001000000 /
b11111111111111111100100001000000 2
b11111111111111111100100001000000 ;
b11111111111111111100100001000000 ?
b11 7
b110111 +
1(
#4916706
0(
#4958373
1$
10
b100 7
b1111111111010101 .
b1111111111010101 :
b11111111111111111101000000100000 !
b11111111111111111101000000100000 ,
b11111111111111111101000000100000 /
b11111111111111111101000000100000 2
b11111111111111111101000000100000 ;
b11111111111111111101000000100000 ?
b11111 )
b11111 -
b11111 9
b111000 +
1(
#5000040
0(
#5041707
b1111111111011011 )
b1111111111011011 -
b1111111111011011 9
b11111 .
b11111 :
b11111111111111111101100111010000 !
b11111111111111111101100111010000 ,
b11111111111111111101100111010000 /
b11111111111111111101100111010000 2
b11111111111111111101100111010000 ;
b11111111111111111101100111010000 ?
b101 7
b111001 +
1(
#5083374
0(
#5125041
b110 7
b1111111111011011 .
b1111111111011011 :
b11111111111111111101111010100000 !
b11111111111111111101111010100000 ,
b11111111111111111101111010100000 /
b11111111111111111101111010100000 2
b11111111111111111101111010100000 ;
b11111111111111111101111010100000 ?
b0 )
b0 -
b0 9
b111010 +
1(
#5166708
0(
#5208375
b1011111 )
b1011111 -
b1011111 9
b0 .
b0 :
b11111111111111111110001111100000 !
b11111111111111111110001111100000 ,
b11111111111111111110001111100000 /
b11111111111111111110001111100000 2
b11111111111111111110001111100000 ;
b11111111111111111110001111100000 ?
b111 7
b111011 +
1(
#5250042
0(
